openmm/amd.py
openmm/mtsintegrator.py
openmm/openmm.py
openmm/testInstallation.py
openmm/vec3.py
openmm/version.py
openmm/_openmm.cp311-win_amd64.pyd
openmm/__init__.py
openmm/app/amberinpcrdfile.py
openmm/app/amberprmtopfile.py
openmm/app/charmmcrdfiles.py
openmm/app/charmmparameterset.py
openmm/app/charmmpsffile.py
openmm/app/checkpointreporter.py
openmm/app/dcdfile.py
openmm/app/dcdreporter.py
openmm/app/desmonddmsfile.py
openmm/app/element.py
openmm/app/forcefield.py
openmm/app/gromacsgrofile.py
openmm/app/gromacstopfile.py
openmm/app/metadynamics.py
openmm/app/modeller.py
openmm/app/pdbfile.py
openmm/app/pdbreporter.py
openmm/app/pdbxfile.py
openmm/app/simulatedtempering.py
openmm/app/simulation.py
openmm/app/statedatareporter.py
openmm/app/tinkerfiles.py
openmm/app/topology.py
openmm/app/xtcfile.py
openmm/app/xtcreporter.py
openmm/app/__init__.py
openmm/app/data/amber03.xml
openmm/app/data/amber03_obc.xml
openmm/app/data/amber10.xml
openmm/app/data/amber10_obc.xml
openmm/app/data/amber14-all.xml
openmm/app/data/amber19-all.xml
openmm/app/data/amber96.xml
openmm/app/data/amber96_obc.xml
openmm/app/data/amber99sb.xml
openmm/app/data/amber99sbildn.xml
openmm/app/data/amber99sbnmr.xml
openmm/app/data/amber99Test.xml
openmm/app/data/amber99_obc.xml
openmm/app/data/amberfb15.xml
openmm/app/data/amoeba2009.xml
openmm/app/data/amoeba2009_gk.xml
openmm/app/data/amoeba2013.xml
openmm/app/data/amoeba2013_gk.xml
openmm/app/data/amoeba2018.xml
openmm/app/data/amoeba2018_gk.xml
openmm/app/data/charmm36.xml
openmm/app/data/charmm36_2024.xml
openmm/app/data/charmm_polar_2013.xml
openmm/app/data/charmm_polar_2019.xml
openmm/app/data/charmm_polar_2023.xml
openmm/app/data/DLPC.pdb
openmm/app/data/DLPE.pdb
openmm/app/data/DMPC.pdb
openmm/app/data/DOPC.pdb
openmm/app/data/DPPC.pdb
openmm/app/data/glycam-hydrogens.xml
openmm/app/data/hydrogens.xml
openmm/app/data/iamoeba.xml
openmm/app/data/opc.xml
openmm-8.4.0.post1.dist-info/METADATA
openmm-8.4.0.post1.dist-info/RECORD
openmm-8.4.0.post1.dist-info/top_level.txt
openmm-8.4.0.post1.dist-info/WHEEL
