Metadata-Version: 2.4
Name: OpenMM
Version: 8.4.0.post1
Summary: Python wrapper for OpenMM (a C++ MD package)
Home-page: https://openmm.org
Download-URL: https://openmm.org
Author: Peter Eastman
License: Python Software Foundation License (BSD-like)
Platform: Linux
Platform: Mac OS X
Platform: Windows
Requires-Dist: numpy
Provides-Extra: cuda12
Requires-Dist: OpenMM-CUDA-12==8.4.0.post1; extra == "cuda12"
Provides-Extra: cuda13
Requires-Dist: OpenMM-CUDA-13==8.4.0.post1; extra == "cuda13"
Provides-Extra: hip6
Requires-Dist: OpenMM-HIP-6==8.4.0.post1; extra == "hip6"
Provides-Extra: hip7
Requires-Dist: OpenMM-HIP-7==8.4.0.post1; extra == "hip7"
Dynamic: author
Dynamic: description
Dynamic: download-url
Dynamic: home-page
Dynamic: license
Dynamic: platform
Dynamic: provides-extra
Dynamic: requires-dist
Dynamic: summary
